pc_target.sv
module pc_target#(
    parameter PC_WIDTH = 32,
    parameter DATA_WIDTH = 32
)(
    input logic [PC_WIDTH-1:0] PC,
    input logic [DATA_WIDTH-1:0] ImmExt,
    output logic [PC_WIDTH-1:0] PC_target
);

    always_comb begin
        PC_target = PC + ImmExt;
    end

endmodule

pc_plus.sv
module pc_plus#(
    parameter PC_WIDTH = 32
)(
    input logic [PC_WIDTH-1:0] PC,
    output logic [PC_WIDTH-1:0] NextPC
);

    always_comb begin
        NextPC = PC + 4;
    end

endmodule

pc_mux.sv
module pc_mux#(
    parameter PC_WIDTH = 32
)(
    input logic PCSrc,
    input logic [PC_WIDTH-1:0] PC_Plus,
    input logic [PC_WIDTH-1:0] PC_Target,
    output logic [PC_WIDTH-1:0] PC_Next
);
    always_comb begin
        PC_Next = PCSrc ? PC_Target : PC_Plus;
    end

endmodule

pc_top.sv
module pc_top#(
    parameter PC_WIDTH = 32
)(
    input logic clk,
    input logic rst,
    input logic PCSrc,
    input logic [PC_WIDTH-1:0] ImmExt,
    output logic [PC_WIDTH-1:0] PC
);

    logic [PC_WIDTH-1:0] PC_Plus;
    logic [PC_WIDTH-1:0] PC_Target;
    logic [PC_WIDTH-1:0] PCNext;

    always_ff @(posedge clk or posedge rst)begin
        if (rst) PC <= 0;
        else PC <= PCNext;
    end

    pc_mux my_pc_mux(
        .PCSrc(PCSrc),
        .PC_Plus(PC_Plus),
        .PC_Target(PC_Target),
        .PC_Next(PCNext)
    );

    pc_plus my_pc_plus(
        .PC(PC),
        .NextPC(PC_Plus)
    );

    pc_target my_pc_target(
        .PC(PC),
        .ImmExt(ImmExt),
        .PC_target(PC_Target)
    );

endmodule

pc_top.vcd
$version Generated by VerilatedVcd $end
$timescale 1ps $end

 $scope module TOP $end
  $var wire 32 & ImmExt [31:0] $end
  $var wire 32 ' PC [31:0] $end
  $var wire  1 % PCSrc $end
  $var wire  1 # clk $end
  $var wire  1 $ rst $end
  $scope module pc_top $end
   $var wire 32 & ImmExt [31:0] $end
   $var wire 32 ' PC [31:0] $end
   $var wire 32 * PCNext [31:0] $end
   $var wire  1 % PCSrc $end
   $var wire 32 ( PC_Plus [31:0] $end
   $var wire 32 ) PC_Target [31:0] $end
   $var wire 32 + PC_WIDTH [31:0] $end
   $var wire  1 # clk $end
   $var wire  1 $ rst $end
   $scope module my_pc_next $end
    $var wire  1 % PCSrc $end
    $var wire 32 * PC_Next [31:0] $end
    $var wire 32 ( PC_Plus [31:0] $end
    $var wire 32 ) PC_Target [31:0] $end
    $var wire 32 + PC_WIDTH [31:0] $end
   $upscope $end
   $scope module my_pc_plus $end
    $var wire 32 ( NextPC [31:0] $end
    $var wire 32 ' PC [31:0] $end
    $var wire 32 + PC_WIDTH [31:0] $end
   $upscope $end
   $scope module my_pc_target $end
    $var wire 32 + DATA_WIDTH [31:0] $end
    $var wire 32 & ImmExt [31:0] $end
    $var wire 32 ' PC [31:0] $end
    $var wire 32 + PC_WIDTH [31:0] $end
    $var wire 32 ) PC_target [31:0] $end
   $upscope $end
  $upscope $end
 $upscope $end
$enddefinitions $end


#0
0#
1$
0%
b00000000000000000000000000000000 &
b00000000000000000000000000000000 '
b00000000000000000000000000000100 (
b00000000000000000000000000000000 )
b00000000000000000000000000000100 *
b00000000000000000000000000100000 +
#1
1#
#2
0#
0$
#3
1#
b00000000000000000000000000000100 '
b00000000000000000000000000001000 (
b00000000000000000000000000000100 )
b00000000000000000000000000001000 *
#4
0#
1%
b00000000000000000000000000000010 &
b00000000000000000000000000000110 )
b00000000000000000000000000000110 *
#5
1#
b00000000000000000000000000000110 '
b00000000000000000000000000001010 (
b00000000000000000000000000001000 )
b00000000000000000000000000001000 *
#6
0#
0%
b00000000000000000000000000001010 *
#7
1#
b00000000000000000000000000001010 '
b00000000000000000000000000001110 (
b00000000000000000000000000001100 )
b00000000000000000000000000001110 *
#8
0#
1%
b00000000000000000000000000001000 &
b00000000000000000000000000010010 )
b00000000000000000000000000010010 *
#9
1#
b00000000000000000000000000010010 '
b00000000000000000000000000010110 (
b00000000000000000000000000011010 )
b00000000000000000000000000011010 *
#10
0#
#11
1#
b00000000000000000000000000011010 '
b00000000000000000000000000011110 (
b00000000000000000000000000100010 )
b00000000000000000000000000100010 *
#12
0#
#13
1#
b00000000000000000000000000100010 '
b00000000000000000000000000100110 (
b00000000000000000000000000101010 )
b00000000000000000000000000101010 *
#14
0#
#15
1#
b00000000000000000000000000101010 '
b00000000000000000000000000101110 (
b00000000000000000000000000110010 )
b00000000000000000000000000110010 *
#16
0#
#17
1#
b00000000000000000000000000110010 '
b00000000000000000000000000110110 (
b00000000000000000000000000111010 )
b00000000000000000000000000111010 *
#18
0#
#19
1#
b00000000000000000000000000111010 '
b00000000000000000000000000111110 (
b00000000000000000000000001000010 )
b00000000000000000000000001000010 *
